commonmethods.py
commonmethods-0.0.1.dist-info/LICENSE.txt
commonmethods-0.0.1.dist-info/METADATA
commonmethods-0.0.1.dist-info/WHEEL
commonmethods-0.0.1.dist-info/top_level.txt
commonmethods-0.0.1.dist-info/RECORD
